mcp_server_monday/__init__.py
mcp_server_monday/board.py
mcp_server_monday/constants.py
mcp_server_monday/document.py
mcp_server_monday/item.py
mcp_server_monday/server.py
mcp_server_monday/tools.py
mcp_server_monday_qi-0.2.13.dist-info/METADATA
mcp_server_monday_qi-0.2.13.dist-info/WHEEL
mcp_server_monday_qi-0.2.13.dist-info/entry_points.txt
mcp_server_monday_qi-0.2.13.dist-info/licenses/LICENSE
mcp_server_monday_qi-0.2.13.dist-info/RECORD
